square/__init__.py
square/apple_pay/__init__.py
square/apple_pay/client.py
square/apple_pay/raw_client.py
square/bank_accounts/__init__.py
square/bank_accounts/client.py
square/bank_accounts/raw_client.py
square/bookings/__init__.py
square/bookings/client.py
square/bookings/custom_attribute_definitions/__init__.py
square/bookings/custom_attribute_definitions/client.py
square/bookings/custom_attribute_definitions/raw_client.py
square/bookings/custom_attributes/__init__.py
square/bookings/custom_attributes/client.py
square/bookings/custom_attributes/raw_client.py
square/bookings/location_profiles/__init__.py
square/bookings/location_profiles/client.py
square/bookings/location_profiles/raw_client.py
square/bookings/raw_client.py
square/bookings/team_member_profiles/__init__.py
square/bookings/team_member_profiles/client.py
square/bookings/team_member_profiles/raw_client.py
square/cards/__init__.py
square/cards/client.py
square/cards/raw_client.py
square/cash_drawers/__init__.py
square/cash_drawers/client.py
square/cash_drawers/raw_client.py
square/cash_drawers/shifts/__init__.py
square/cash_drawers/shifts/client.py
square/cash_drawers/shifts/raw_client.py
square/catalog/__init__.py
square/catalog/client.py
square/catalog/images/__init__.py
square/catalog/images/client.py
square/catalog/images/raw_client.py
square/catalog/object/__init__.py
square/catalog/object/client.py
square/catalog/object/raw_client.py
square/catalog/raw_client.py
square/checkout/__init__.py
square/checkout/client.py
square/checkout/payment_links/__init__.py
square/checkout/payment_links/client.py
square/checkout/payment_links/raw_client.py
square/checkout/raw_client.py
square/client.py
square/core/__init__.py
square/core/api_error.py
square/core/client_wrapper.py
square/core/datetime_utils.py
square/core/file.py
square/core/http_client.py
square/core/http_response.py
square/core/jsonable_encoder.py
square/core/pagination.py
square/core/pydantic_utilities.py
square/core/query_encoder.py
squareup-42.1.0.20250416.dist-info/LICENSE
squareup-42.1.0.20250416.dist-info/METADATA
squareup-42.1.0.20250416.dist-info/WHEEL
squareup-42.1.0.20250416.dist-info/RECORD
